[
  {
    "Username": "Jmike",
    "Email": "Test@lol.com",
    "Password": "test123",
    "Portfolio": "portfolio.pdf",
    "Description": "I'm flash",
    "CareerTitle": ".net full stack developer",
    "Photo": {
      "Url": "https://randomPic.com"
    },
    
    "SearchWordList": [
      {
        "Word": "Web Developement"
      }
    ],
    "Projects": [
      {
        "Title": "Davolt did",
        "Description": "Full stack app,",
        "GitRepositoryUrl": "Https://github.com",
        "ProjectImage": {
          "Url": "Https://random.com"
        },
        "Industry": 
          {
            "Name": "Artificial Intelligence",
            "Projects": [
              {
                "Title": "Devolt did"
              }
            ]
          }
        ,
        "Tags": [
          {
            "TagName": "CS"
          }
        ],
     
        "UsersMembers": [
          {
            "Username": "Tom bufa"
          },
          {
            "Username": "Tim lol"
          },
          {
            "Username": "Tam adsd"
          }
        ],
        "ChatMessagesBoards": [
          {
            "Title": "Hello world",
            "Body": "I love programming",
            "Username": "Tom bufa"
          }
        ]
        
      }
    ]
  },
  {
    "Username": "John Doe",
    "Email": "Test@lol.com",
    "Password": "test123",
    "Portfolio": "portfolio.pdf",
    "Description": "I'm flash",
    "CareerTitle": ".net full stack developer",
    "Photo": {
      "Url": "https://randomPic.com"
    },
    
    "SearchWordList": [
      {
        "Word": "Web Developement"
      }
    ],
    "Projects": [
      {
        "Title": "Davolt",
        "Description": "Full stack app,",
        "GitRepositoryUrl": "Https://github.com",
        "ProjectImage": {
          "Url": "Https://random.com"
        },
        "Industry": 
          {
            "Name": "Web Developement",
            "Projects": [
              {
                "Title": "Devolt"
              }
            ]
          }
        ,
        "Tags": [
          {
            "TagName": "CS"
          }
        ],
      
        "UsersMembers": [
          {
            "Username": "Tom"
          },
          {
            "Username": "Tim"
          },
          {
            "Username": "Tam"
          }
        ],
        "ChatMessagesBoards": [
          {
            "Title": "Hello world",
            "Body": "I love programming",
            "Username": "Tom"
          }
        ]
      
      }
    ]
  },
  {
    "Username": "Elisabet",
    "Email": "Test@lol.com",
    "Password": "test123",
    "Portfolio": "portfolio.pdf",
    "Description": "I'm flash",
    "CareerTitle": ".net full stack developer",
    "Photo": {
      "Url": "https://randomPic.com"
    },
   
    "SearchWordList": [
      {
        "Word": "Web Developement"
      }
    ],
    "Projects": [
      {
        "Title": "MonkeRule",
        "Description": "Full stack app,",
        "GitRepositoryUrl": "Https://github.com",
        "ProjectImage": {
          "Url": "Https://random.com"
        },
        "Industry": 
          {
            "Name": "Automation",
            "Projects": [
              {
                "Title": "MonkeRule"
              }
            ]
          }
        ,
        "Tags": [
          {
            "TagName": "CS"
          }
        ],

        "UsersMembers": [
          {
            "Username": "Slave 1"
          },
          {
            "Username": "Slave 2"
          },
          {
            "Username": "Slave 3"
          }
        ],
        "ChatMessagesBoards": [
          {
            "Title": "Hello world",
            "Body": "I love programming",
            "Username": "Slave 1"
          }
        ]
     
      }
    ]
  },
  {
    "Username": "Cuckerino",
    "Email": "Test@lol.com",
    "Password": "test123",
    "Portfolio": "portfolio.pdf",
    "Description": "I'm flash",
    "CareerTitle": ".net full stack developer",
    "Photo": {
      "Url": "https://randomPic.com"
    },
    "SearchWordList": [
      {
        "Word": "Web Developement"
      }
    ],
    "Projects": [
      {
        "Title": "Banana",
        "Description": "Full stack app,",
        "GitRepositoryUrl": "Https://github.com",
        "ProjectImage": {
          "Url": "Https://random.com"
        },
        "Industry": 
          {
            "Name": "Earth is flat society",
            "Projects": [
              {
                "Title": "Banana"
              }
            ]
          }
        ,
        "Tags": [
          {
            "TagName": "CS"
          }
        ],
    
        "UsersMembers": [
          {
            "Username": "BUBA"
          },
          {
            "Username": "BIBI"
          },
          {
            "Username": "BOBO"
          }
        ],
        "ChatMessagesBoards": [
          {
            "Title": "Hello world",
            "Body": "I love programming",
            "Username": "BIBI"
          }
        ]
  
      }
    ]
  },
  {
    "Username": "John mow",
    "Email": "Test@lol.com",
    "Password": "test123",
    "Portfolio": "portfolio.pdf",
    "Description": "I'm flash",
    "CareerTitle": ".net full stack developer",
    "Photo": {
      "Url": "https://randomPic.com"
    },

    "SearchWordList": [
      {
        "Word": "Web Developement"
      }
    ],
    "Projects": [
      {
        "Title": "Sigma",
        "Description": "Full stack app,",
        "GitRepositoryUrl": "Https://github.com",
        "ProjectImage": {
          "Url": "Https://random.com"
        },
        "Industry": 
          {
            "Name": "Music",
            "Projects": [
              {
                "Title": "Sigma"
              }
            ]
          }
        ,
        "Tags": [
          {
            "TagName": "CS"
          }
        ],
      
        "UsersMembers": [
          {
            "Username": "Tomtom"
          },
          {
            "Username": "Timtom"
          },
          {
            "Username": "Tamtom"
          }
        ],
        "ChatMessagesBoards": [
          {
            "Title": "Hello world",
            "Body": "I love programming",
            "Username": "Tomtom"
          }
        ]
      
      }
    ]
  },
  {
    "Username": "candice",
    "Email": "Test@lol.com",
    "Password": "test123",
    "Portfolio": "portfolio.pdf",
    "Description": "I'm flash",
    "CareerTitle": ".net full stack developer",
    "Photo": {
      "Url": "https://randomPic.com"
    },

    "SearchWordList": [
      {
        "Word": "Web Developement"
      }
    ],
    "Projects": [
      {
        "Title": "To the moon",
        "Description": "Full stack app,",
        "GitRepositoryUrl": "Https://github.com",
        "ProjectImage": {
          "Url": "Https://random.com"
        },
        "Industry": 
          {
            "Name": "Art",
            "Projects": [
              {
                "Title": "Art"
              }
            ]
          }
        ,
        "Tags": [
          {
            "TagName": "CS"
          }
        ],
        
        "UsersMembers": [
          {
            "Username": "noice"
          },
          {
            "Username": "naice"
          },
          {
            "Username": "neice"
          }
        ],
        "ChatMessagesBoards": [
          {
            "Title": "Hello world",
            "Body": "I love programming",
            "Username": "Tom"
          }
        ]
       
      }
    ]
  }
]
